sphinxcontrib_htsql-0.1.5-py2.7-nspkg.pth
sphinxcontrib_htsql-0.1.5.dist-info/RECORD
sphinxcontrib_htsql-0.1.5.dist-info/DESCRIPTION.rst
sphinxcontrib_htsql-0.1.5.dist-info/metadata.json
sphinxcontrib_htsql-0.1.5.dist-info/METADATA
sphinxcontrib_htsql-0.1.5.dist-info/top_level.txt
sphinxcontrib_htsql-0.1.5.dist-info/namespace_packages.txt
sphinxcontrib_htsql-0.1.5.dist-info/WHEEL
sphinxcontrib/htsql.css
sphinxcontrib/htsql.py
