Metadata-Version: 2.0
Name: sphinxcontrib-htsql
Version: 0.1.5
Summary: HTSQL extension for Sphinx
Home-page: http://bitbucket.org/prometheus/sphinxcontrib-htsql
Author: Kirill Simonov (Prometheus Research, LLC)
Author-email: xi@resolvent.net
License: BSD
Download-URL: http://pypi.python.org/pypi/sphinxcontrib-htsql
Platform: any
Classifier: Development Status :: 4 - Beta
Classifier: Intended Audience :: Developers
Classifier: License :: OSI Approved :: BSD License
Classifier: Operating System :: OS Independent
Classifier: Programming Language :: Python
Classifier: Topic :: Documentation
Classifier: Topic :: Text Processing
Requires-Dist: Sphinx
